shaq/__init__.py
shaq/__main__.py
shaq/_cli.py
shaq-0.0.5.dist-info/entry_points.txt
shaq-0.0.5.dist-info/LICENSE
shaq-0.0.5.dist-info/WHEEL
shaq-0.0.5.dist-info/METADATA
shaq-0.0.5.dist-info/RECORD
