Metadata-Version: 2.1
Name: shaq
Version: 0.0.5
Summary: A bare-bones Shazam CLI client
Author-email: William Woodruff <william@yossarian.net>
Requires-Python: >=3.10
Classifier: License :: OSI Approved :: MIT License
Classifier: Programming Language :: Python :: 3 :: Only
Classifier: Programming Language :: Python :: 3
Classifier: Programming Language :: Python :: 3.10
Classifier: Programming Language :: Python :: 3.11
Classifier: Topic :: Multimedia :: Sound/Audio
Classifier: Topic :: Multimedia :: Sound/Audio :: Analysis
Requires-Dist: pyaudio ~= 0.2.13
Requires-Dist: pydub ~= 0.25.1
Requires-Dist: rich ~= 13.4
Requires-Dist: shazamio ~= 0.6.0
Requires-Dist: build ; extra == "dev"
Requires-Dist: shaq[test,lint] ; extra == "dev"
Requires-Dist: mypy ; extra == "lint"
Requires-Dist: ruff ; extra == "lint"
Requires-Dist: pytest ; extra == "test"
Requires-Dist: pytest-cov ; extra == "test"
Requires-Dist: pretend ; extra == "test"
Project-URL: Homepage, https://pypi.org/project/shaq/
Project-URL: Issues, https://github.com/woodruffw/shaq/issues
Project-URL: Source, https://github.com/woodruffw/shaq
Provides-Extra: dev
Provides-Extra: lint
Provides-Extra: test
